moto_bas2lst/__init__.py
moto_bas2lst/__main__.py
moto_bas2lst/bas2lst.py
moto_fdar/__init__.py
moto_fdar/__main__.py
moto_lib/__init__.py
moto_lib/basic/__init__.py
moto_lib/basic/converter_from_listing.py
moto_lib/basic/tokenizer.py
moto_lib/fs_disk/__init__.py
moto_lib/fs_disk/block_allocation.py
moto_lib/fs_disk/catalog.py
moto_lib/fs_disk/cli.py
moto_lib/fs_disk/controller.py
moto_lib/fs_disk/image.py
moto_lib/fs_disk/image_manager.py
moto_lib/fs_disk/image_worker/__init__.py
moto_lib/fs_disk/image_worker/base.py
moto_lib/fs_disk/image_worker/content_enumerator.py
moto_lib/fs_disk/image_worker/content_extractor.py
moto_lib/fs_disk/image_worker/content_injector.py
moto_lib/fs_disk/listener/__init__.py
moto_lib/fs_disk/listener/_counters.py
moto_lib/fs_disk/listener/consts.py
moto_lib/fs_disk/listener/listener.py
moto_lib/fs_disk/listener/quiet.py
moto_lib/fs_disk/listener/verbose.py
moto_lib/fs_tape/__init__.py
moto_lib/fs_tape/block.py
moto_lib/fs_tape/block_descriptor.py
moto_lib/fs_tape/consts.py
moto_lib/fs_tape/image_manager.py
moto_lib/fs_tape/image_worker/__init__.py
moto_lib/fs_tape/image_worker/base.py
moto_lib/fs_tape/image_worker/content_enumerator.py
moto_lib/fs_tape/image_worker/content_extractor.py
moto_lib/fs_tape/image_worker/content_injector.py
moto_lib/fs_tape/listeners.py
moto_lib/fs_tape/tape.py
moto_lst2bas/__init__.py
moto_lst2bas/__main__.py
moto_lst2bas/lst2bas.py
moto_nl/__init__.py
moto_nl/__main__.py
moto_nl/nl.py
moto_prettier/__init__.py
moto_prettier/__main__.py
moto_prettier/prettier.py
moto_sdar/__init__.py
moto_sdar/__main__.py
moto_tar/__init__.py
moto_tar/__main__.py
moto_tar/tar.py
moto_tools_by_sporniket-0.0.6.dist-info/METADATA
moto_tools_by_sporniket-0.0.6.dist-info/WHEEL
moto_tools_by_sporniket-0.0.6.dist-info/entry_points.txt
moto_tools_by_sporniket-0.0.6.dist-info/RECORD
