Metadata-Version: 2.1
Name: moto-tools-by-sporniket
Version: 0.0.6
Summary: A python library with a set of command line interfaces that will assist a developper of software running on emulators of the family of computers made by Thomson during the 1980s, models "MO" and models "TO".
Keywords: thomson MO5,toolchain
Author-Email: Sporniket <sporniket.studio@gmail.com>
License: GPL-3.0-or-later
Project-URL: homepage, https://github.com/sporniket/moto-tools
Project-URL: repository, https://github.com/sporniket/moto-tools
Project-URL: bug-tracker, https://github.com/sporniket/moto-tools/issues
Requires-Python: >=3.10
